math_util.py
math_util-0.0.2.dist-info/LICENSE
math_util-0.0.2.dist-info/METADATA
math_util-0.0.2.dist-info/WHEEL
math_util-0.0.2.dist-info/top_level.txt
math_util-0.0.2.dist-info/RECORD
